atom_tickets/__init__.py
atom_tickets/_base_client.py
atom_tickets/_client.py
atom_tickets/_compat.py
atom_tickets/_constants.py
atom_tickets/_exceptions.py
atom_tickets/_files.py
atom_tickets/_models.py
atom_tickets/_qs.py
atom_tickets/_resource.py
atom_tickets/_response.py
atom_tickets/_streaming.py
atom_tickets/_types.py
atom_tickets/_version.py
atom_tickets/py.typed
atom_tickets/_utils/__init__.py
atom_tickets/_utils/_logs.py
atom_tickets/_utils/_proxy.py
atom_tickets/_utils/_reflection.py
atom_tickets/_utils/_resources_proxy.py
atom_tickets/_utils/_streams.py
atom_tickets/_utils/_sync.py
atom_tickets/_utils/_transform.py
atom_tickets/_utils/_typing.py
atom_tickets/_utils/_utils.py
atom_tickets/lib/.keep
atom_tickets/resources/__init__.py
atom_tickets/resources/partner/__init__.py
atom_tickets/resources/partner/partner.py
atom_tickets/resources/partner/v1/__init__.py
atom_tickets/resources/partner/v1/v1.py
atom_tickets/resources/partner/v1/production/__init__.py
atom_tickets/resources/partner/v1/production/details.py
atom_tickets/resources/partner/v1/production/ids.py
atom_tickets/resources/partner/v1/production/production.py
atom_tickets/resources/partner/v1/production/search.py
atom_tickets/resources/partner/v1/showtime/__init__.py
atom_tickets/resources/partner/v1/showtime/details.py
atom_tickets/resources/partner/v1/showtime/showtime.py
atom_tickets/resources/partner/v1/venue/__init__.py
atom_tickets/resources/partner/v1/venue/details.py
atom_tickets/resources/partner/v1/venue/showtimes.py
atom_tickets/resources/partner/v1/venue/venue.py
atom_tickets/resources/partner/v1/venue/by_vendor_venue_id/__init__.py
atom_tickets/resources/partner/v1/venue/by_vendor_venue_id/by_vendor_venue_id.py
atom_tickets/resources/partner/v1/venue/by_vendor_venue_id/showtimes.py
atom_tickets/types/__init__.py
atom_tickets/types/partner/__init__.py
atom_tickets/types/partner/v1/__init__.py
atom_tickets/types/partner/v1/production/__init__.py
atom_tickets-1.2.0.dist-info/METADATA
atom_tickets-1.2.0.dist-info/WHEEL
atom_tickets-1.2.0.dist-info/licenses/LICENSE
atom_tickets-1.2.0.dist-info/RECORD
